hrelutils/__init__.py
hrelutils/functional.py
hrelutils/time.py
hrelutils/update.py
hrelutils-1.1.dist-info/DESCRIPTION.rst
hrelutils-1.1.dist-info/METADATA
hrelutils-1.1.dist-info/RECORD
hrelutils-1.1.dist-info/WHEEL
hrelutils-1.1.dist-info/metadata.json
hrelutils-1.1.dist-info/top_level.txt
