Metadata-Version: 2.0
Name: hrelutils
Version: 1.1
Summary: Hrel utils
Home-page: https://gitlab.com/hrel3/hrelutils/
Author: Justin Barber
Author-email: justin@hrel.ca
License: UNKNOWN
Platform: UNKNOWN
Requires-Python: >=3.6
